doc2mcp.py
doc2mcp-0.1.1.dist-info/licenses/LICENSE
doc2mcp-0.1.1.dist-info/METADATA
doc2mcp-0.1.1.dist-info/WHEEL
doc2mcp-0.1.1.dist-info/top_level.txt
doc2mcp-0.1.1.dist-info/RECORD
